cogni/__init__.py
cogni/cli.py
cogni/magicimport.py
cogni/entities/__init__.py
cogni/entities/conversation.py
cogni/entities/message.py
cogni/middlewares/llm.py
cogni/tools/llm.py
cogni/wrappers/__init__.py
cogni/wrappers/agent.py
cogni/wrappers/func_wrapper.py
cogni/wrappers/instances_store.py
cogni/wrappers/middleware.py
cogni/wrappers/tool.py
cogni-0.1.0.dist-info/METADATA
cogni-0.1.0.dist-info/WHEEL
cogni-0.1.0.dist-info/licenses/LICENSE
cogni-0.1.0.dist-info/RECORD
