Metadata-Version: 2.4
Name: cogni
Version: 0.1.0
Summary: Low boilerplate agentic
Project-URL: Homepage, https://github.com/BrutLogic/cogni
Project-URL: Issues, https://github.com/BrutLogic/cogni/issues
Author-email: Valentin DION <v@lentin.fr>
License-File: LICENSE
Classifier: License :: OSI Approved :: MIT License
Classifier: Operating System :: OS Independent
Classifier: Programming Language :: Python :: 3
Requires-Python: >=3.8
